cookiecutter/__init__.py
cookiecutter/__main__.py
cookiecutter/cli.py
cookiecutter/config.py
cookiecutter/context_manager.py
cookiecutter/environment.py
cookiecutter/exceptions.py
cookiecutter/extensions.py
cookiecutter/find.py
cookiecutter/generate.py
cookiecutter/hooks.py
cookiecutter/log.py
cookiecutter/main.py
cookiecutter/operator.py
cookiecutter/prompt.py
cookiecutter/render.py
cookiecutter/replay.py
cookiecutter/repository.py
cookiecutter/utils.py
cookiecutter/vcs.py
cookiecutter/zipfile.py
cookiecutter/operators/__init__.py
cookiecutter/operators/aws.py
cookiecutter/operators/azure.py
cookiecutter/operators/block.py
cookiecutter/operators/checkbox.py
cookiecutter/operators/command.py
cookiecutter/operators/confirm.py
cookiecutter/operators/dicts.py
cookiecutter/operators/digitalocean.py
cookiecutter/operators/editor.py
cookiecutter/operators/expand.py
cookiecutter/operators/file.py
cookiecutter/operators/gcp.py
cookiecutter/operators/input.py
cookiecutter/operators/jinja.py
cookiecutter/operators/json.py
cookiecutter/operators/listdir.py
cookiecutter/operators/lists.py
cookiecutter/operators/nukikata.py
cookiecutter/operators/password.py
cookiecutter/operators/paths.py
cookiecutter/operators/print.py
cookiecutter/operators/random.py
cookiecutter/operators/rawlist.py
cookiecutter/operators/select.py
cookiecutter/operators/stat.py
cookiecutter/operators/strings.py
cookiecutter/operators/table.py
cookiecutter/operators/terraform.py
cookiecutter/operators/web.py
cookiecutter/operators/yaml.py
nukikata-2.0.0.3.dist-info/AUTHORS.md
nukikata-2.0.0.3.dist-info/LICENSE
nukikata-2.0.0.3.dist-info/METADATA
nukikata-2.0.0.3.dist-info/WHEEL
nukikata-2.0.0.3.dist-info/entry_points.txt
nukikata-2.0.0.3.dist-info/top_level.txt
nukikata-2.0.0.3.dist-info/RECORD
