Metadata-Version: 2.1
Name: nukikata
Version: 2.0.0.3
Summary: Fork of cookiecutter - https://github.com/cookiecutter/cookiecutter The most popular command-line utility to create projects from project templates, e.g. creating a Python package project from a Python package project template.
Home-page: https://github.com/insight-infrastructure/nukikata
Author: Fork by Rob Cannon
Author-email: rob.cannon@insightinfrastructure.com
License: BSD
Keywords: cookiecutter,Python,projects,project templates,Jinja2,skeleton,scaffolding,project directory,package,packaging
Platform: UNKNOWN
Classifier: Development Status :: 5 - Production/Stable
Classifier: Environment :: Console
Classifier: Intended Audience :: Developers
Classifier: Natural Language :: English
Classifier: License :: OSI Approved :: BSD License
Classifier: Programming Language :: Python :: 3 :: Only
Classifier: Programming Language :: Python :: 3
Classifier: Programming Language :: Python :: 3.6
Classifier: Programming Language :: Python :: 3.7
Classifier: Programming Language :: Python :: 3.8
Classifier: Programming Language :: Python :: Implementation :: CPython
Classifier: Programming Language :: Python :: Implementation :: PyPy
Classifier: Programming Language :: Python
Classifier: Topic :: Software Development
Requires-Python: >=3.6
Requires-Dist: binaryornot (>=0.4.4)
Requires-Dist: Jinja2 (<3.0.0)
Requires-Dist: click (>=7.0)
Requires-Dist: poyo (>=0.5.0)
Requires-Dist: jinja2-time (>=0.2.0)
Requires-Dist: python-slugify (>=4.0.0)
Requires-Dist: requests (>=2.23.0)
Requires-Dist: MarkupSafe (<2.0.0)
Requires-Dist: PyInquirer (>=1.0.3)
Requires-Dist: PyYAML (>=5.3)
Requires-Dist: boto3 (>=1.14.0google-api-python-client>=1.9)
Requires-Dist: google-api-python-client (>=1.9)
Requires-Dist: azure-mgmt-compute (>=13.0.0)
Requires-Dist: azure-mgmt-subscription (>=0.6.0)
Requires-Dist: pyhcl (>=0.4.4)
Requires-Dist: distro (>=1.5.0)
Requires-Dist: rich (>=3.3.0)
Requires-Dist: dopy (>=0.3.7)
